dbtlogs/__init__.py
dbtlogs/main.py
dbtlogs1-0.2.dist-info/METADATA
dbtlogs1-0.2.dist-info/WHEEL
dbtlogs1-0.2.dist-info/entry_points.txt
dbtlogs1-0.2.dist-info/top_level.txt
dbtlogs1-0.2.dist-info/RECORD
