Metadata-Version: 2.1
Name: dbtlogs1
Version: 0.2
Requires-Dist: click
Requires-Dist: databricks-sql-connector
Requires-Dist: requests
Requires-Dist: pytz
Requires-Dist: typing
Requires-Dist: datetime
Requires-Dist: apache-airflow
Requires-Dist: snowflake-sqlalchemy
